<?xml version='1.0' encoding='UTF-8' standalone='yes' ?><hierarchy rotation="0"><node index="0" text="" resource-id="" class="android.widget.FrameLayout" package="com.novacut.editor" content-desc="" checkable="false" checked="false" clickable="false" enabled="true" focusable="false" focused="false" scrollable="false" long-clickable="false" password="false" selected="false" bounds="[0,0][1080,2400]" drawing-order="0" hint=""><node index="0" text="" resource-id="" class="android.widget.LinearLayout" package="com.novacut.editor" content-desc="" checkable="false" checked="false" clickable="false" enabled="true" focusable="false" focused="false" scrollable="false" long-clickable="false" password="false" selected="false" bounds="[0,0][1080,2400]" drawing-order="1" hint=""><node index="0" text="" resource-id="android:id/content" class="android.widget.FrameLayout" package="com.novacut.editor" content-desc="" checkable="false" checked="false" clickable="false" enabled="true" focusable="false" focused="false" scrollable="false" long-clickable="false" password="false" selected="false" bounds="[0,0][1080,2400]" drawing-order="2" hint=""><node index="0" text="" resource-id="" class="androidx.compose.ui.platform.ComposeView" package="com.novacut.editor" content-desc="" checkable="false" checked="false" clickable="false" enabled="true" focusable="false" focused="false" scrollable="false" long-clickable="false" password="false" selected="false" bounds="[0,0][1080,2400]" drawing-order="1" hint=""><node index="0" text="" resource-id="" class="android.view.View" package="com.novacut.editor" content-desc="" checkable="false" checked="false" clickable="false" enabled="true" focusable="false" focused="false" scrollable="false" long-clickable="false" password="false" selected="false" bounds="[0,0][1080,2400]" drawing-order="0" hint=""><node index="0" text="" resource-id="" class="android.view.View" package="com.novacut.editor" content-desc="" checkable="false" checked="false" clickable="false" enabled="true" focusable="true" focused="true" scrollable="false" long-clickable="false" password="false" selected="false" bounds="[0,63][1080,2337]" drawing-order="0" hint=""><node index="0" text="" resource-id="" class="android.view.View" package="com.novacut.editor" content-desc="" checkable="false" checked="false" clickable="false" enabled="true" focusable="false" focused="false" scrollable="false" long-clickable="false" password="false" selected="false" bounds="[0,63][1080,226]" drawing-order="0" hint=""><node index="0" text="" resource-id="" class="android.view.View" package="com.novacut.editor" content-desc="" checkable="false" checked="false" clickable="false" enabled="true" focusable="false" focused="false" scrollable="false" long-clickable="false" password="false" selected="false" bounds="[26,95][126,195]" drawing-order="0" hint=""><node index="0" text="" resource-id="" class="android.view.View" package="com.novacut.editor" content-desc="" checkable="false" checked="false" clickable="true" enabled="true" focusable="true" focused="false" scrollable="false" long-clickable="false" password="false" selected="false" bounds="[13,82][139,208]" drawing-order="0" hint=""><node index="0" text="" resource-id="" class="android.view.View" package="com.novacut.editor" content-desc="Home" checkable="false" checked="false" clickable="false" enabled="true" focusable="false" focused="false" scrollable="false" long-clickable="false" password="false" selected="false" bounds="[50,119][103,172]" drawing-order="0" hint="" /><node index="1" text="" resource-id="" class="android.widget.Button" package="com.novacut.editor" content-desc="" checkable="false" checked="false" clickable="false" enabled="true" focusable="false" focused="false" scrollable="false" long-clickable="false" password="false" selected="false" bounds="[26,95][126,195]" drawing-order="0" hint="" /></node></node><node index="1" text="Untitled" resource-id="" class="android.widget.TextView" package="com.novacut.editor" content-desc="" checkable="false" checked="false" clickable="false" enabled="true" focusable="false" focused="false" scrollable="false" long-clickable="false" password="false" selected="false" bounds="[152,88][299,137]" drawing-order="0" hint="" /><node index="2" text="" resource-id="" class="android.view.View" package="com.novacut.editor" content-desc="" checkable="false" checked="false" clickable="false" enabled="true" focusable="false" focused="false" scrollable="false" long-clickable="false" password="false" selected="false" bounds="[152,145][240,201]" drawing-order="0" hint=""><node index="0" text="Pro" resource-id="" class="android.widget.TextView" package="com.novacut.editor" content-desc="" checkable="false" checked="false" clickable="false" enabled="true" focusable="false" focused="false" scrollable="false" long-clickable="false" password="false" selected="false" bounds="[173,156][219,190]" drawing-order="0" hint="" /></node><node index="3" text="" resource-id="" class="android.view.View" package="com.novacut.editor" content-desc="" checkable="false" checked="false" clickable="false" enabled="true" focusable="false" focused="false" scrollable="false" long-clickable="false" password="false" selected="false" bounds="[562,100][740,189]" drawing-order="0" hint=""><node index="0" text="" resource-id="" class="android.view.View" package="com.novacut.editor" content-desc="" checkable="false" checked="false" clickable="true" enabled="false" focusable="false" focused="false" scrollable="false" long-clickable="false" password="false" selected="false" bounds="[545,83][634,209]" drawing-order="0" hint=""><node index="0" text="" resource-id="" class="android.view.View" package="com.novacut.editor" content-desc="Undo" checkable="false" checked="false" clickable="false" enabled="true" focusable="false" focused="false" scrollable="false" long-clickable="false" password="false" selected="false" bounds="[584,122][631,169]" drawing-order="0" hint="" /><node index="1" text="" resource-id="" class="android.widget.Button" package="com.novacut.editor" content-desc="" checkable="false" checked="false" clickable="false" enabled="true" focusable="false" focused="false" scrollable="false" long-clickable="false" password="false" selected="false" bounds="[563,101][652,189]" drawing-order="0" hint="" /></node><node index="1" text="" resource-id="" class="android.view.View" package="com.novacut.editor" content-desc="" checkable="false" checked="false" clickable="true" enabled="false" focusable="false" focused="false" scrollable="false" long-clickable="false" password="false" selected="false" bounds="[634,83][760,209]" drawing-order="0" hint=""><node index="0" text="" resource-id="" class="android.view.View" package="com.novacut.editor" content-desc="Redo" checkable="false" checked="false" clickable="false" enabled="true" focusable="false" focused="false" scrollable="false" long-clickable="false" password="false" selected="false" bounds="[673,122][720,169]" drawing-order="0" hint="" /><node index="1" text="" resource-id="" class="android.widget.Button" package="com.novacut.editor" content-desc="" checkable="false" checked="false" clickable="false" enabled="true" focusable="false" focused="false" scrollable="false" long-clickable="false" password="false" selected="false" bounds="[652,101][740,189]" drawing-order="0" hint="" /></node></node><node index="4" text="" resource-id="" class="android.view.View" package="com.novacut.editor" content-desc="" checkable="false" checked="false" clickable="false" enabled="true" focusable="false" focused="false" scrollable="false" long-clickable="false" password="false" selected="false" bounds="[761,95][861,195]" drawing-order="0" hint=""><node index="0" text="" resource-id="" class="android.view.View" package="com.novacut.editor" content-desc="" checkable="false" checked="false" clickable="true" enabled="true" focusable="true" focused="false" scrollable="false" long-clickable="false" password="false" selected="false" bounds="[748,82][874,208]" drawing-order="0" hint=""><node index="0" text="" resource-id="" class="android.view.View" package="com.novacut.editor" content-desc="More" checkable="false" checked="false" clickable="false" enabled="true" focusable="false" focused="false" scrollable="false" long-clickable="false" password="false" selected="false" bounds="[785,119][838,172]" drawing-order="0" hint="" /><node index="1" text="" resource-id="" class="android.widget.Button" package="com.novacut.editor" content-desc="" checkable="false" checked="false" clickable="false" enabled="true" focusable="false" focused="false" scrollable="false" long-clickable="false" password="false" selected="false" bounds="[761,95][861,195]" drawing-order="0" hint="" /></node></node><node index="5" text="" resource-id="" class="android.view.View" package="com.novacut.editor" content-desc="" checkable="false" checked="false" clickable="true" enabled="true" focusable="true" focused="false" scrollable="false" long-clickable="false" password="false" selected="false" bounds="[882,82][1054,208]" drawing-order="0" hint=""><node index="0" text="Export" resource-id="" class="android.widget.TextView" package="com.novacut.editor" content-desc="" checkable="false" checked="false" clickable="false" enabled="true" focusable="false" focused="false" scrollable="false" long-clickable="false" password="false" selected="false" bounds="[919,125][1017,165]" drawing-order="0" hint="" /><node index="1" text="" resource-id="" class="android.widget.Button" package="com.novacut.editor" content-desc="" checkable="false" checked="false" clickable="false" enabled="true" focusable="false" focused="false" scrollable="false" long-clickable="false" password="false" selected="false" bounds="[882,95][1054,195]" drawing-order="0" hint="" /></node></node><node index="1" text="" resource-id="" class="android.view.View" package="com.novacut.editor" content-desc="" checkable="false" checked="false" clickable="false" enabled="true" focusable="false" focused="false" scrollable="false" long-clickable="false" password="false" selected="false" bounds="[26,247][1054,1143]" drawing-order="0" hint=""><node index="0" text="" resource-id="" class="androidx.compose.ui.viewinterop.ViewFactoryHolder" package="com.novacut.editor" content-desc="" checkable="false" checked="false" clickable="false" enabled="true" focusable="false" focused="false" scrollable="false" long-clickable="false" password="false" selected="false" bounds="[52,273][1028,1117]" drawing-order="1" hint=""><node index="0" text="" resource-id="" class="android.widget.FrameLayout" package="com.novacut.editor" content-desc="" checkable="false" checked="false" clickable="false" enabled="true" focusable="false" focused="false" scrollable="false" long-clickable="false" password="false" selected="false" bounds="[52,273][1028,1117]" drawing-order="1" hint=""><node index="0" text="" resource-id="com.novacut.editor:id/exo_ad_overlay" class="android.widget.FrameLayout" package="com.novacut.editor" content-desc="" checkable="false" checked="false" clickable="false" enabled="true" focusable="false" focused="false" scrollable="false" long-clickable="false" password="false" selected="false" bounds="[52,273][1028,1117]" drawing-order="2" hint="" /><node index="1" text="" resource-id="com.novacut.editor:id/exo_overlay" class="android.widget.FrameLayout" package="com.novacut.editor" content-desc="" checkable="false" checked="false" clickable="false" enabled="true" focusable="false" focused="false" scrollable="false" long-clickable="false" password="false" selected="false" bounds="[52,273][1028,1117]" drawing-order="3" hint="" /><node index="2" text="" resource-id="com.novacut.editor:id/exo_content_frame" class="android.widget.FrameLayout" package="com.novacut.editor" content-desc="" checkable="false" checked="false" clickable="false" enabled="true" focusable="false" focused="false" scrollable="false" long-clickable="false" password="false" selected="false" bounds="[52,273][1028,1117]" drawing-order="1" hint=""><node index="0" text="" resource-id="" class="android.view.SurfaceView" package="com.novacut.editor" content-desc="" checkable="false" checked="false" clickable="false" enabled="true" focusable="false" focused="false" scrollable="false" long-clickable="false" password="false" selected="false" bounds="[52,273][1028,1117]" drawing-order="1" hint="" /><node index="1" text="" resource-id="com.novacut.editor:id/exo_shutter" class="android.view.View" package="com.novacut.editor" content-desc="" checkable="false" checked="false" clickable="false" enabled="true" focusable="false" focused="false" scrollable="false" long-clickable="false" password="false" selected="false" bounds="[52,273][1028,1117]" drawing-order="2" hint="" /><node index="2" text="" resource-id="com.novacut.editor:id/exo_subtitles" class="android.widget.FrameLayout" package="com.novacut.editor" content-desc="" checkable="false" checked="false" clickable="false" enabled="true" focusable="false" focused="false" scrollable="false" long-clickable="false" password="false" selected="false" bounds="[52,273][1028,1117]" drawing-order="5" hint=""><node index="0" text="" resource-id="" class="android.view.View" package="com.novacut.editor" content-desc="" checkable="false" checked="false" clickable="false" enabled="true" focusable="false" focused="false" scrollable="false" long-clickable="false" password="false" selected="false" bounds="[52,273][1028,1117]" drawing-order="1" hint="" /></node></node></node></node><node index="1" text="" resource-id="" class="android.view.View" package="com.novacut.editor" content-desc="" checkable="false" checked="false" clickable="false" enabled="true" focusable="false" focused="false" scrollable="false" long-clickable="false" password="false" selected="false" bounds="[78,299][343,368]" drawing-order="0" hint=""><node index="0" text="Live Preview" resource-id="" class="android.widget.TextView" package="com.novacut.editor" content-desc="" checkable="false" checked="false" clickable="false" enabled="true" focusable="false" focused="false" scrollable="false" long-clickable="false" password="false" selected="false" bounds="[141,315][317,352]" drawing-order="0" hint="" /></node><node index="2" text="" resource-id="" class="android.view.View" package="com.novacut.editor" content-desc="" checkable="false" checked="false" clickable="false" enabled="true" focusable="false" focused="false" scrollable="false" long-clickable="false" password="false" selected="false" bounds="[902,299][1002,399]" drawing-order="0" hint=""><node index="0" text="" resource-id="" class="android.view.View" package="com.novacut.editor" content-desc="" checkable="false" checked="false" clickable="true" enabled="true" focusable="true" focused="false" scrollable="false" long-clickable="false" password="false" selected="false" bounds="[889,286][1015,412]" drawing-order="0" hint=""><node index="0" text="" resource-id="" class="android.view.View" package="com.novacut.editor" content-desc="Scopes" checkable="false" checked="false" clickable="false" enabled="true" focusable="false" focused="false" scrollable="false" long-clickable="false" password="false" selected="false" bounds="[929,326][976,373]" drawing-order="0" hint="" /><node index="1" text="" resource-id="" class="android.widget.Button" package="com.novacut.editor" content-desc="" checkable="false" checked="false" clickable="false" enabled="true" focusable="false" focused="false" scrollable="false" long-clickable="false" password="false" selected="false" bounds="[902,299][1002,399]" drawing-order="0" hint="" /></node></node></node><node index="2" text="" resource-id="" class="android.view.View" package="com.novacut.editor" content-desc="" checkable="false" checked="false" clickable="false" enabled="true" focusable="false" focused="false" scrollable="false" long-clickable="false" password="false" selected="false" bounds="[26,1169][1054,1331]" drawing-order="0" hint=""><node index="0" text="00:00" resource-id="" class="android.widget.TextView" package="com.novacut.editor" content-desc="" checkable="false" checked="false" clickable="false" enabled="true" focusable="false" focused="false" scrollable="false" long-clickable="false" password="false" selected="false" bounds="[63,1207][170,1256]" drawing-order="0" hint="" /><node index="1" text="00:05" resource-id="" class="android.widget.TextView" package="com.novacut.editor" content-desc="" checkable="false" checked="false" clickable="false" enabled="true" focusable="false" focused="false" scrollable="false" long-clickable="false" password="false" selected="false" bounds="[63,1256][139,1293]" drawing-order="0" hint="" /><node index="2" text="" resource-id="" class="android.view.View" package="com.novacut.editor" content-desc="" checkable="false" checked="false" clickable="false" enabled="true" focusable="false" focused="false" scrollable="false" long-clickable="false" password="false" selected="false" bounds="[907,1195][1017,1305]" drawing-order="0" hint=""><node index="0" text="" resource-id="" class="android.view.View" package="com.novacut.editor" content-desc="" checkable="false" checked="false" clickable="true" enabled="true" focusable="true" focused="false" scrollable="false" long-clickable="false" password="false" selected="false" bounds="[899,1187][1025,1313]" drawing-order="0" hint=""><node index="0" text="" resource-id="" class="android.view.View" package="com.novacut.editor" content-desc="Play" checkable="false" checked="false" clickable="false" enabled="true" focusable="false" focused="false" scrollable="false" long-clickable="false" password="false" selected="false" bounds="[931,1219][994,1282]" drawing-order="0" hint="" /><node index="1" text="" resource-id="" class="android.widget.Button" package="com.novacut.editor" content-desc="" checkable="false" checked="false" clickable="false" enabled="true" focusable="false" focused="false" scrollable="false" long-clickable="false" password="false" selected="false" bounds="[907,1195][1017,1305]" drawing-order="0" hint="" /></node></node></node><node index="3" text="" resource-id="" class="android.view.View" package="com.novacut.editor" content-desc="" checkable="false" checked="false" clickable="false" enabled="true" focusable="false" focused="false" scrollable="false" long-clickable="false" password="false" selected="false" bounds="[0,1352][1080,2121]" drawing-order="0" hint=""><node index="0" text="Timeline" resource-id="" class="android.widget.TextView" package="com.novacut.editor" content-desc="" checkable="false" checked="false" clickable="false" enabled="true" focusable="false" focused="false" scrollable="false" long-clickable="false" password="false" selected="false" bounds="[32,1386][197,1435]" drawing-order="0" hint="" /><node index="1" text="0:00 / 0:05" resource-id="" class="android.widget.TextView" package="com.novacut.editor" content-desc="" checkable="false" checked="false" clickable="false" enabled="true" focusable="false" focused="false" scrollable="false" long-clickable="false" password="false" selected="false" bounds="[32,1435][179,1472]" drawing-order="0" hint="" /><node index="2" text="" resource-id="" class="android.view.View" package="com.novacut.editor" content-desc="" checkable="false" checked="false" clickable="false" enabled="true" focusable="false" focused="false" scrollable="false" long-clickable="false" password="false" selected="false" bounds="[629,1384][718,1473]" drawing-order="0" hint=""><node index="0" text="" resource-id="" class="android.view.View" package="com.novacut.editor" content-desc="" checkable="false" checked="false" clickable="true" enabled="true" focusable="true" focused="false" scrollable="false" long-clickable="false" password="false" selected="false" bounds="[612,1367][722,1473]" drawing-order="0" hint=""><node index="0" text="" resource-id="" class="android.view.View" package="com.novacut.editor" content-desc="Zoom Out" checkable="false" checked="false" clickable="false" enabled="true" focusable="false" focused="false" scrollable="false" long-clickable="false" password="false" selected="false" bounds="[654,1409][696,1451]" drawing-order="0" hint="" /><node index="1" text="" resource-id="" class="android.widget.Button" package="com.novacut.editor" content-desc="" checkable="false" checked="false" clickable="false" enabled="true" focusable="false" focused="false" scrollable="false" long-clickable="false" password="false" selected="false" bounds="[630,1385][718,1473]" drawing-order="0" hint="" /></node></node><node index="3" text="" resource-id="" class="android.view.View" package="com.novacut.editor" content-desc="" checkable="false" checked="false" clickable="false" enabled="true" focusable="false" focused="false" scrollable="false" long-clickable="false" password="false" selected="false" bounds="[739,1384][828,1473]" drawing-order="0" hint=""><node index="0" text="" resource-id="" class="android.view.View" package="com.novacut.editor" content-desc="" checkable="false" checked="false" clickable="true" enabled="true" focusable="true" focused="false" scrollable="false" long-clickable="false" password="false" selected="false" bounds="[722,1367][832,1473]" drawing-order="0" hint=""><node index="0" text="" resource-id="" class="android.view.View" package="com.novacut.editor" content-desc="Fit" checkable="false" checked="false" clickable="false" enabled="true" focusable="false" focused="false" scrollable="false" long-clickable="false" password="false" selected="false" bounds="[764,1409][806,1451]" drawing-order="0" hint="" /><node index="1" text="" resource-id="" class="android.widget.Button" package="com.novacut.editor" content-desc="" checkable="false" checked="false" clickable="false" enabled="true" focusable="false" focused="false" scrollable="false" long-clickable="false" password="false" selected="false" bounds="[740,1385][828,1473]" drawing-order="0" hint="" /></node></node><node index="4" text="" resource-id="" class="android.view.View" package="com.novacut.editor" content-desc="" checkable="false" checked="false" clickable="false" enabled="true" focusable="false" focused="false" scrollable="false" long-clickable="false" password="false" selected="false" bounds="[849,1384][938,1473]" drawing-order="0" hint=""><node index="0" text="" resource-id="" class="android.view.View" package="com.novacut.editor" content-desc="" checkable="false" checked="false" clickable="true" enabled="true" focusable="true" focused="false" scrollable="false" long-clickable="false" password="false" selected="false" bounds="[832,1367][942,1473]" drawing-order="0" hint=""><node index="0" text="" resource-id="" class="android.view.View" package="com.novacut.editor" content-desc="Zoom In" checkable="false" checked="false" clickable="false" enabled="true" focusable="false" focused="false" scrollable="false" long-clickable="false" password="false" selected="false" bounds="[874,1409][916,1451]" drawing-order="0" hint="" /><node index="1" text="" resource-id="" class="android.widget.Button" package="com.novacut.editor" content-desc="" checkable="false" checked="false" clickable="false" enabled="true" focusable="false" focused="false" scrollable="false" long-clickable="false" password="false" selected="false" bounds="[850,1385][938,1473]" drawing-order="0" hint="" /></node></node><node index="5" text="" resource-id="" class="android.view.View" package="com.novacut.editor" content-desc="" checkable="false" checked="false" clickable="false" enabled="true" focusable="false" focused="false" scrollable="false" long-clickable="false" password="false" selected="false" bounds="[959,1384][1048,1473]" drawing-order="0" hint=""><node index="0" text="" resource-id="" class="android.view.View" package="com.novacut.editor" content-desc="" checkable="false" checked="false" clickable="true" enabled="true" focusable="true" focused="false" scrollable="false" long-clickable="false" password="false" selected="false" bounds="[942,1367][1068,1473]" drawing-order="0" hint=""><node index="0" text="" resource-id="" class="android.view.View" package="com.novacut.editor" content-desc="Add Marker" checkable="false" checked="false" clickable="false" enabled="true" focusable="false" focused="false" scrollable="false" long-clickable="false" password="false" selected="false" bounds="[984,1409][1026,1451]" drawing-order="0" hint="" /><node index="1" text="" resource-id="" class="android.widget.Button" package="com.novacut.editor" content-desc="" checkable="false" checked="false" clickable="false" enabled="true" focusable="false" focused="false" scrollable="false" long-clickable="false" password="false" selected="false" bounds="[960,1385][1048,1473]" drawing-order="0" hint="" /></node></node><node index="6" text="" resource-id="" class="android.widget.HorizontalScrollView" package="com.novacut.editor" content-desc="" checkable="false" checked="false" clickable="false" enabled="true" focusable="false" focused="false" scrollable="true" long-clickable="false" password="false" selected="false" bounds="[0,1473][1080,1585]" drawing-order="0" hint=""><node index="0" text="" resource-id="" class="android.view.View" package="com.novacut.editor" content-desc="" checkable="false" checked="false" clickable="false" enabled="true" focusable="false" focused="false" scrollable="false" long-clickable="false" password="false" selected="false" bounds="[32,1499][179,1559]" drawing-order="0" hint=""><node index="0" text="Arrange" resource-id="" class="android.widget.TextView" package="com.novacut.editor" content-desc="" checkable="false" checked="false" clickable="false" enabled="true" focusable="false" focused="false" scrollable="false" long-clickable="false" password="false" selected="false" bounds="[53,1512][158,1546]" drawing-order="0" hint="" /></node><node index="1" text="" resource-id="" class="android.view.View" package="com.novacut.editor" content-desc="" checkable="false" checked="false" clickable="false" enabled="true" focusable="false" focused="false" scrollable="false" long-clickable="false" password="false" selected="false" bounds="[200,1499][396,1559]" drawing-order="0" hint=""><node index="0" text="Zoom 100%" resource-id="" class="android.widget.TextView" package="com.novacut.editor" content-desc="" checkable="false" checked="false" clickable="false" enabled="true" focusable="false" focused="false" scrollable="false" long-clickable="false" password="false" selected="false" bounds="[221,1512][375,1546]" drawing-order="0" hint="" /></node><node index="2" text="" resource-id="" class="android.view.View" package="com.novacut.editor" content-desc="" checkable="false" checked="false" clickable="false" enabled="true" focusable="false" focused="false" scrollable="false" long-clickable="false" password="false" selected="false" bounds="[417,1499][588,1559]" drawing-order="0" hint=""><node index="0" text="View 0:04" resource-id="" class="android.widget.TextView" package="com.novacut.editor" content-desc="" checkable="false" checked="false" clickable="false" enabled="true" focusable="false" focused="false" scrollable="false" long-clickable="false" password="false" selected="false" bounds="[438,1512][567,1546]" drawing-order="0" hint="" /></node><node index="3" text="" resource-id="" class="android.view.View" package="com.novacut.editor" content-desc="" checkable="false" checked="false" clickable="false" enabled="true" focusable="false" focused="false" scrollable="false" long-clickable="false" password="false" selected="false" bounds="[609,1499][782,1559]" drawing-order="0" hint=""><node index="0" text="0 markers" resource-id="" class="android.widget.TextView" package="com.novacut.editor" content-desc="" checkable="false" checked="false" clickable="false" enabled="true" focusable="false" focused="false" scrollable="false" long-clickable="false" password="false" selected="false" bounds="[630,1512][761,1546]" drawing-order="0" hint="" /></node><node index="4" text="" resource-id="" class="android.view.View" package="com.novacut.editor" content-desc="" checkable="false" checked="false" clickable="false" enabled="true" focusable="false" focused="false" scrollable="false" long-clickable="false" password="false" selected="false" bounds="[803,1499][1059,1559]" drawing-order="0" hint=""><node index="0" text="Snap to Markers" resource-id="" class="android.widget.TextView" package="com.novacut.editor" content-desc="" checkable="false" checked="false" clickable="false" enabled="true" focusable="false" focused="false" scrollable="false" long-clickable="false" password="false" selected="false" bounds="[824,1512][1038,1546]" drawing-order="0" hint="" /></node></node><node index="7" text="Tracks" resource-id="" class="android.widget.TextView" package="com.novacut.editor" content-desc="" checkable="false" checked="false" clickable="false" enabled="true" focusable="false" focused="false" scrollable="false" long-clickable="false" password="false" selected="false" bounds="[37,1611][131,1648]" drawing-order="0" hint="" /><node index="8" text="1 clip" resource-id="" class="android.widget.TextView" package="com.novacut.editor" content-desc="" checkable="false" checked="false" clickable="false" enabled="true" focusable="false" focused="false" scrollable="false" long-clickable="false" password="false" selected="false" bounds="[37,1651][109,1685]" drawing-order="0" hint="" /><node index="9" text="" resource-id="" class="android.view.View" package="com.novacut.editor" content-desc="" checkable="false" checked="false" clickable="false" enabled="true" focusable="false" focused="false" scrollable="false" long-clickable="false" password="false" selected="false" bounds="[26,1685][310,1837]" drawing-order="0" hint=""><node index="0" text="" resource-id="" class="android.view.View" package="com.novacut.editor" content-desc="" checkable="false" checked="false" clickable="false" enabled="true" focusable="false" focused="false" scrollable="false" long-clickable="false" password="false" selected="false" bounds="[47,1707][111,1743]" drawing-order="0" hint="" /><node index="1" text="Video 1" resource-id="" class="android.widget.TextView" package="com.novacut.editor" content-desc="" checkable="false" checked="false" clickable="false" enabled="true" focusable="false" focused="false" scrollable="false" long-clickable="false" password="false" selected="false" bounds="[127,1703][196,1740]" drawing-order="0" hint="" /><node index="2" text="Locked" resource-id="" class="android.widget.TextView" package="com.novacut.editor" content-desc="" checkable="false" checked="false" clickable="false" enabled="true" focusable="false" focused="false" scrollable="false" long-clickable="false" password="false" selected="false" bounds="[127,1740][196,1743]" drawing-order="0" hint="" /><node index="3" text="" resource-id="" class="android.view.View" package="com.novacut.editor" content-desc="" checkable="false" checked="false" clickable="false" enabled="true" focusable="false" focused="false" scrollable="false" long-clickable="false" password="false" selected="false" bounds="[226,1707][289,1743]" drawing-order="0" hint=""><node index="0" text="" resource-id="" class="android.view.View" package="com.novacut.editor" content-desc="" checkable="false" checked="false" clickable="true" enabled="true" focusable="true" focused="false" scrollable="false" long-clickable="false" password="false" selected="false" bounds="[196,1677][322,1743]" drawing-order="0" hint=""><node index="0" text="" resource-id="" class="android.view.View" package="com.novacut.editor" content-desc="Collapse track" checkable="false" checked="false" clickable="false" enabled="true" focusable="false" focused="false" scrollable="false" long-clickable="false" password="false" selected="false" bounds="[243,1724][275,1743]" drawing-order="0" hint="" /><node index="1" text="" resource-id="" class="android.widget.Button" package="com.novacut.editor" content-desc="" checkable="false" checked="false" clickable="false" enabled="true" focusable="false" focused="false" scrollable="false" long-clickable="false" password="false" selected="false" bounds="[227,1708][289,1770]" drawing-order="0" hint="" /></node></node><node index="4" text="" resource-id="" class="android.view.View" package="com.novacut.editor" content-desc="" checkable="false" checked="false" clickable="false" enabled="true" focusable="false" focused="false" scrollable="false" long-clickable="false" password="false" selected="false" bounds="[47,1790][91,1819]" drawing-order="0" hint=""><node index="0" text="" resource-id="" class="android.view.View" package="com.novacut.editor" content-desc="" checkable="false" checked="false" clickable="true" enabled="true" focusable="true" focused="false" scrollable="false" long-clickable="false" password="false" selected="false" bounds="[17,1743][91,1869]" drawing-order="0" hint=""><node index="0" text="" resource-id="" class="android.view.View" package="com.novacut.editor" content-desc="Toggle track visibility" checkable="false" checked="false" clickable="false" enabled="true" focusable="false" focused="false" scrollable="false" long-clickable="false" password="false" selected="false" bounds="[64,1791][91,1819]" drawing-order="0" hint="" /><node index="1" text="" resource-id="" class="android.widget.Button" package="com.novacut.editor" content-desc="" checkable="false" checked="false" clickable="false" enabled="true" focusable="false" focused="false" scrollable="false" long-clickable="false" password="false" selected="false" bounds="[48,1791][110,1819]" drawing-order="0" hint="" /></node></node><node index="5" text="" resource-id="" class="android.view.View" package="com.novacut.editor" content-desc="" checkable="false" checked="false" clickable="false" enabled="true" focusable="false" focused="false" scrollable="false" long-clickable="false" password="false" selected="false" bounds="[121,1790][165,1819]" drawing-order="0" hint=""><node index="0" text="" resource-id="" class="android.view.View" package="com.novacut.editor" content-desc="" checkable="false" checked="false" clickable="true" enabled="true" focusable="true" focused="false" scrollable="false" long-clickable="false" password="false" selected="false" bounds="[91,1743][165,1853]" drawing-order="0" hint=""><node index="0" text="" resource-id="" class="android.view.View" package="com.novacut.editor" content-desc="Toggle track mute" checkable="false" checked="false" clickable="false" enabled="true" focusable="false" focused="false" scrollable="false" long-clickable="false" password="false" selected="false" bounds="[138,1791][165,1819]" drawing-order="0" hint="" /><node index="1" text="" resource-id="" class="android.widget.Button" package="com.novacut.editor" content-desc="" checkable="false" checked="false" clickable="false" enabled="true" focusable="false" focused="false" scrollable="false" long-clickable="false" password="false" selected="false" bounds="[122,1791][184,1819]" drawing-order="0" hint="" /></node></node><node index="6" text="" resource-id="" class="android.view.View" package="com.novacut.editor" content-desc="" checkable="false" checked="false" clickable="false" enabled="true" focusable="false" focused="false" scrollable="false" long-clickable="false" password="false" selected="false" bounds="[195,1790][216,1819]" drawing-order="0" hint=""><node index="0" text="" resource-id="" class="android.view.View" package="com.novacut.editor" content-desc="" checkable="false" checked="false" clickable="true" enabled="true" focusable="true" focused="false" scrollable="false" long-clickable="false" password="false" selected="false" bounds="[165,1743][216,1853]" drawing-order="0" hint=""><node index="0" text="" resource-id="" class="android.view.View" package="com.novacut.editor" content-desc="Toggle track lock" checkable="false" checked="false" clickable="false" enabled="true" focusable="false" focused="false" scrollable="false" long-clickable="false" password="false" selected="false" bounds="[212,1791][216,1819]" drawing-order="0" hint="" /><node index="1" text="" resource-id="" class="android.widget.Button" package="com.novacut.editor" content-desc="" checkable="false" checked="false" clickable="false" enabled="true" focusable="false" focused="false" scrollable="false" long-clickable="false" password="false" selected="false" bounds="[196,1791][258,1819]" drawing-order="0" hint="" /></node></node><node index="7" text="" resource-id="" class="android.view.View" package="com.novacut.editor" content-desc="" checkable="false" checked="false" clickable="false" enabled="true" focusable="false" focused="false" scrollable="false" long-clickable="false" password="false" selected="false" bounds="[269,1790][289,1819]" drawing-order="0" hint=""><node index="0" text="" resource-id="" class="android.view.View" package="com.novacut.editor" content-desc="" checkable="false" checked="false" clickable="true" enabled="true" focusable="true" focused="false" scrollable="false" long-clickable="false" password="false" selected="false" bounds="[216,1743][342,1869]" drawing-order="0" hint=""><node index="0" text="" resource-id="" class="android.view.View" package="com.novacut.editor" content-desc="Track options" checkable="false" checked="false" clickable="false" enabled="true" focusable="false" focused="false" scrollable="false" long-clickable="false" password="false" selected="false" bounds="[269,1791][289,1819]" drawing-order="0" hint="" /><node index="1" text="" resource-id="" class="android.widget.Button" package="com.novacut.editor" content-desc="" checkable="false" checked="false" clickable="false" enabled="true" focusable="false" focused="false" scrollable="false" long-clickable="false" password="false" selected="false" bounds="[269,1791][289,1819]" drawing-order="0" hint="" /></node></node></node><node index="10" text="" resource-id="" class="android.view.View" package="com.novacut.editor" content-desc="" checkable="false" checked="false" clickable="false" enabled="true" focusable="false" focused="false" scrollable="false" long-clickable="false" password="false" selected="false" bounds="[26,1853][310,2005]" drawing-order="0" hint=""><node index="0" text="" resource-id="" class="android.view.View" package="com.novacut.editor" content-desc="" checkable="false" checked="false" clickable="false" enabled="true" focusable="false" focused="false" scrollable="false" long-clickable="false" password="false" selected="false" bounds="[47,1875][111,1911]" drawing-order="0" hint="" /><node index="1" text="Audio 2" resource-id="" class="android.widget.TextView" package="com.novacut.editor" content-desc="" checkable="false" checked="false" clickable="false" enabled="true" focusable="false" focused="false" scrollable="false" long-clickable="false" password="false" selected="false" bounds="[127,1871][196,1908]" drawing-order="0" hint="" /><node index="2" text="Locked" resource-id="" class="android.widget.TextView" package="com.novacut.editor" content-desc="" checkable="false" checked="false" clickable="false" enabled="true" focusable="false" focused="false" scrollable="false" long-clickable="false" password="false" selected="false" bounds="[127,1908][196,1911]" drawing-order="0" hint="" /><node index="3" text="" resource-id="" class="android.view.View" package="com.novacut.editor" content-desc="" checkable="false" checked="false" clickable="false" enabled="true" focusable="false" focused="false" scrollable="false" long-clickable="false" password="false" selected="false" bounds="[226,1875][289,1911]" drawing-order="0" hint=""><node index="0" text="" resource-id="" class="android.view.View" package="com.novacut.editor" content-desc="" checkable="false" checked="false" clickable="true" enabled="true" focusable="true" focused="false" scrollable="false" long-clickable="false" password="false" selected="false" bounds="[196,1845][322,1911]" drawing-order="0" hint=""><node index="0" text="" resource-id="" class="android.view.View" package="com.novacut.editor" content-desc="Collapse track" checkable="false" checked="false" clickable="false" enabled="true" focusable="false" focused="false" scrollable="false" long-clickable="false" password="false" selected="false" bounds="[243,1892][275,1911]" drawing-order="0" hint="" /><node index="1" text="" resource-id="" class="android.widget.Button" package="com.novacut.editor" content-desc="" checkable="false" checked="false" clickable="false" enabled="true" focusable="false" focused="false" scrollable="false" long-clickable="false" password="false" selected="false" bounds="[227,1876][289,1938]" drawing-order="0" hint="" /></node></node><node index="4" text="" resource-id="" class="android.view.View" package="com.novacut.editor" content-desc="" checkable="false" checked="false" clickable="false" enabled="true" focusable="false" focused="false" scrollable="false" long-clickable="false" password="false" selected="false" bounds="[47,1958][91,1987]" drawing-order="0" hint=""><node index="0" text="" resource-id="" class="android.view.View" package="com.novacut.editor" content-desc="" checkable="false" checked="false" clickable="true" enabled="true" focusable="true" focused="false" scrollable="false" long-clickable="false" password="false" selected="false" bounds="[17,1911][91,2037]" drawing-order="0" hint=""><node index="0" text="" resource-id="" class="android.view.View" package="com.novacut.editor" content-desc="Toggle waveform" checkable="false" checked="false" clickable="false" enabled="true" focusable="false" focused="false" scrollable="false" long-clickable="false" password="false" selected="false" bounds="[64,1959][91,1987]" drawing-order="0" hint="" /><node index="1" text="" resource-id="" class="android.widget.Button" package="com.novacut.editor" content-desc="" checkable="false" checked="false" clickable="false" enabled="true" focusable="false" focused="false" scrollable="false" long-clickable="false" password="false" selected="false" bounds="[48,1959][110,1987]" drawing-order="0" hint="" /></node></node><node index="5" text="" resource-id="" class="android.view.View" package="com.novacut.editor" content-desc="" checkable="false" checked="false" clickable="false" enabled="true" focusable="false" focused="false" scrollable="false" long-clickable="false" password="false" selected="false" bounds="[121,1958][165,1987]" drawing-order="0" hint=""><node index="0" text="" resource-id="" class="android.view.View" package="com.novacut.editor" content-desc="" checkable="false" checked="false" clickable="true" enabled="true" focusable="true" focused="false" scrollable="false" long-clickable="false" password="false" selected="false" bounds="[91,1911][165,2037]" drawing-order="0" hint=""><node index="0" text="" resource-id="" class="android.view.View" package="com.novacut.editor" content-desc="Toggle track mute" checkable="false" checked="false" clickable="false" enabled="true" focusable="false" focused="false" scrollable="false" long-clickable="false" password="false" selected="false" bounds="[138,1959][165,1987]" drawing-order="0" hint="" /><node index="1" text="" resource-id="" class="android.widget.Button" package="com.novacut.editor" content-desc="" checkable="false" checked="false" clickable="false" enabled="true" focusable="false" focused="false" scrollable="false" long-clickable="false" password="false" selected="false" bounds="[122,1959][184,1987]" drawing-order="0" hint="" /></node></node><node index="6" text="" resource-id="" class="android.view.View" package="com.novacut.editor" content-desc="" checkable="false" checked="false" clickable="false" enabled="true" focusable="false" focused="false" scrollable="false" long-clickable="false" password="false" selected="false" bounds="[195,1958][216,1987]" drawing-order="0" hint=""><node index="0" text="" resource-id="" class="android.view.View" package="com.novacut.editor" content-desc="" checkable="false" checked="false" clickable="true" enabled="true" focusable="true" focused="false" scrollable="false" long-clickable="false" password="false" selected="false" bounds="[165,1911][216,2037]" drawing-order="0" hint=""><node index="0" text="" resource-id="" class="android.view.View" package="com.novacut.editor" content-desc="Toggle track lock" checkable="false" checked="false" clickable="false" enabled="true" focusable="false" focused="false" scrollable="false" long-clickable="false" password="false" selected="false" bounds="[212,1959][216,1987]" drawing-order="0" hint="" /><node index="1" text="" resource-id="" class="android.widget.Button" package="com.novacut.editor" content-desc="" checkable="false" checked="false" clickable="false" enabled="true" focusable="false" focused="false" scrollable="false" long-clickable="false" password="false" selected="false" bounds="[196,1959][258,1987]" drawing-order="0" hint="" /></node></node><node index="7" text="" resource-id="" class="android.view.View" package="com.novacut.editor" content-desc="" checkable="false" checked="false" clickable="false" enabled="true" focusable="false" focused="false" scrollable="false" long-clickable="false" password="false" selected="false" bounds="[269,1958][289,1987]" drawing-order="0" hint=""><node index="0" text="" resource-id="" class="android.view.View" package="com.novacut.editor" content-desc="" checkable="false" checked="false" clickable="true" enabled="true" focusable="true" focused="false" scrollable="false" long-clickable="false" password="false" selected="false" bounds="[216,1911][342,2037]" drawing-order="0" hint=""><node index="0" text="" resource-id="" class="android.view.View" package="com.novacut.editor" content-desc="Track options" checkable="false" checked="false" clickable="false" enabled="true" focusable="false" focused="false" scrollable="false" long-clickable="false" password="false" selected="false" bounds="[269,1959][289,1987]" drawing-order="0" hint="" /><node index="1" text="" resource-id="" class="android.widget.Button" package="com.novacut.editor" content-desc="" checkable="false" checked="false" clickable="false" enabled="true" focusable="false" focused="false" scrollable="false" long-clickable="false" password="false" selected="false" bounds="[269,1959][289,1987]" drawing-order="0" hint="" /></node></node></node><node index="11" text="" resource-id="" class="android.view.View" package="com.novacut.editor" content-desc="" checkable="false" checked="false" clickable="false" enabled="true" focusable="false" focused="false" scrollable="false" long-clickable="false" password="false" selected="false" bounds="[658,1714][776,1770]" drawing-order="0" hint=""><node index="0" text="Video" resource-id="" class="android.widget.TextView" package="com.novacut.editor" content-desc="" checkable="false" checked="false" clickable="false" enabled="true" focusable="false" focused="false" scrollable="false" long-clickable="false" password="false" selected="false" bounds="[679,1725][755,1759]" drawing-order="0" hint="" /></node><node index="12" text="Video Clip" resource-id="" class="android.widget.TextView" package="com.novacut.editor" content-desc="" checkable="false" checked="false" clickable="false" enabled="true" focusable="false" focused="false" scrollable="false" long-clickable="false" password="false" selected="false" bounds="[658,1770][812,1810]" drawing-order="0" hint="" /><node index="13" text="" resource-id="" class="android.view.View" package="com.novacut.editor" content-desc="" checkable="false" checked="false" clickable="false" enabled="true" focusable="false" focused="false" scrollable="false" long-clickable="false" password="false" selected="false" bounds="[658,1821][758,1824]" drawing-order="0" hint="" /><node index="14" text="No clips yet" resource-id="" class="android.widget.TextView" package="com.novacut.editor" content-desc="" checkable="false" checked="false" clickable="false" enabled="true" focusable="false" focused="false" scrollable="false" long-clickable="false" password="false" selected="false" bounds="[616,1920][770,1954]" drawing-order="0" hint="" /></node><node index="4" text="" resource-id="" class="android.view.View" package="com.novacut.editor" content-desc="" checkable="false" checked="false" clickable="false" enabled="true" focusable="false" focused="false" scrollable="false" long-clickable="false" password="false" selected="false" bounds="[0,2121][1080,2337]" drawing-order="0" hint=""><node index="0" text="" resource-id="" class="android.view.View" package="com.novacut.editor" content-desc="" checkable="false" checked="false" clickable="false" enabled="true" focusable="false" focused="false" scrollable="true" long-clickable="false" password="false" selected="false" bounds="[21,2142][1059,2316]" drawing-order="0" hint=""><node index="0" text="" resource-id="" class="android.view.View" package="com.novacut.editor" content-desc="" checkable="false" checked="false" clickable="true" enabled="true" focusable="true" focused="false" scrollable="false" long-clickable="false" password="false" selected="false" bounds="[21,2142][210,2316]" drawing-order="0" hint=""><node index="0" text="" resource-id="" class="android.view.View" package="com.novacut.editor" content-desc="Edit" checkable="false" checked="false" clickable="false" enabled="true" focusable="false" focused="false" scrollable="false" long-clickable="false" password="false" selected="false" bounds="[89,2181][142,2234]" drawing-order="0" hint="" /><node index="1" text="Edit" resource-id="" class="android.widget.TextView" package="com.novacut.editor" content-desc="" checkable="false" checked="false" clickable="false" enabled="true" focusable="false" focused="false" scrollable="false" long-clickable="false" password="false" selected="false" bounds="[93,2263][138,2295]" drawing-order="0" hint="" /></node><node index="1" text="" resource-id="" class="android.view.View" package="com.novacut.editor" content-desc="" checkable="false" checked="false" clickable="true" enabled="true" focusable="true" focused="false" scrollable="false" long-clickable="false" password="false" selected="false" bounds="[210,2142][399,2316]" drawing-order="0" hint=""><node index="0" text="" resource-id="" class="android.view.View" package="com.novacut.editor" content-desc="Audio" checkable="false" checked="false" clickable="false" enabled="true" focusable="false" focused="false" scrollable="false" long-clickable="false" password="false" selected="false" bounds="[278,2181][331,2234]" drawing-order="0" hint="" /><node index="1" text="Audio" resource-id="" class="android.widget.TextView" package="com.novacut.editor" content-desc="" checkable="false" checked="false" clickable="false" enabled="true" focusable="false" focused="false" scrollable="false" long-clickable="false" password="false" selected="false" bounds="[271,2263][338,2295]" drawing-order="0" hint="" /></node><node index="2" text="" resource-id="" class="android.view.View" package="com.novacut.editor" content-desc="" checkable="false" checked="false" clickable="true" enabled="true" focusable="true" focused="false" scrollable="false" long-clickable="false" password="false" selected="false" bounds="[399,2142][588,2316]" drawing-order="0" hint=""><node index="0" text="" resource-id="" class="android.view.View" package="com.novacut.editor" content-desc="Text" checkable="false" checked="false" clickable="false" enabled="true" focusable="false" focused="false" scrollable="false" long-clickable="false" password="false" selected="false" bounds="[467,2181][520,2234]" drawing-order="0" hint="" /><node index="1" text="Text" resource-id="" class="android.widget.TextView" package="com.novacut.editor" content-desc="" checkable="false" checked="false" clickable="false" enabled="true" focusable="false" focused="false" scrollable="false" long-clickable="false" password="false" selected="false" bounds="[468,2263][519,2295]" drawing-order="0" hint="" /></node><node index="3" text="" resource-id="" class="android.view.View" package="com.novacut.editor" content-desc="" checkable="false" checked="false" clickable="true" enabled="true" focusable="true" focused="false" scrollable="false" long-clickable="false" password="false" selected="false" bounds="[588,2142][777,2316]" drawing-order="0" hint=""><node index="0" text="" resource-id="" class="android.view.View" package="com.novacut.editor" content-desc="Effects" checkable="false" checked="false" clickable="false" enabled="true" focusable="false" focused="false" scrollable="false" long-clickable="false" password="false" selected="false" bounds="[656,2181][709,2234]" drawing-order="0" hint="" /><node index="1" text="Effects" resource-id="" class="android.widget.TextView" package="com.novacut.editor" content-desc="" checkable="false" checked="false" clickable="false" enabled="true" focusable="false" focused="false" scrollable="false" long-clickable="false" password="false" selected="false" bounds="[641,2263][724,2295]" drawing-order="0" hint="" /></node><node index="4" text="" resource-id="" class="android.view.View" package="com.novacut.editor" content-desc="" checkable="false" checked="false" clickable="true" enabled="true" focusable="true" focused="false" scrollable="false" long-clickable="false" password="false" selected="false" bounds="[777,2142][966,2316]" drawing-order="0" hint=""><node index="0" text="" resource-id="" class="android.view.View" package="com.novacut.editor" content-desc="Aspect" checkable="false" checked="false" clickable="false" enabled="true" focusable="false" focused="false" scrollable="false" long-clickable="false" password="false" selected="false" bounds="[845,2181][898,2234]" drawing-order="0" hint="" /><node index="1" text="Aspect" resource-id="" class="android.widget.TextView" package="com.novacut.editor" content-desc="" checkable="false" checked="false" clickable="false" enabled="true" focusable="false" focused="false" scrollable="false" long-clickable="false" password="false" selected="false" bounds="[831,2263][913,2295]" drawing-order="0" hint="" /></node><node index="5" text="" resource-id="" class="android.view.View" package="com.novacut.editor" content-desc="" checkable="false" checked="false" clickable="true" enabled="true" focusable="true" focused="false" scrollable="false" long-clickable="false" password="false" selected="false" bounds="[966,2142][1080,2316]" drawing-order="0" hint=""><node index="0" text="" resource-id="" class="android.view.View" package="com.novacut.editor" content-desc="Tools" checkable="false" checked="false" clickable="false" enabled="true" focusable="false" focused="false" scrollable="false" long-clickable="false" password="false" selected="false" bounds="[1034,2181][1059,2234]" drawing-order="0" hint="" /><node index="1" text="Tools" resource-id="" class="android.widget.TextView" package="com.novacut.editor" content-desc="" checkable="false" checked="false" clickable="false" enabled="true" focusable="false" focused="false" scrollable="false" long-clickable="false" password="false" selected="false" bounds="[1029,2263][1059,2295]" drawing-order="0" hint="" /></node></node></node></node></node></node></node></node></node></hierarchy>